aiohopcolony/__about__.py
aiohopcolony/__init__.py
aiohopcolony/auth/__init__.py
aiohopcolony/auth/auth_credentials.py
aiohopcolony/auth/auth_token.py
aiohopcolony/auth/auth_user.py
aiohopcolony/docs/__init__.py
aiohopcolony/docs/docs_document.py
aiohopcolony/docs/docs_index.py
aiohopcolony/drive/__init__.py
aiohopcolony/drive/drive_bucket.py
aiohopcolony/drive/drive_object.py
aiohopcolony/drive/drive_signer.py
aiohopcolony/jobs/__init__.py
aiohopcolony/jobs/jobs.py
aiohopcolony/jobs/jobs_pipelines.py
aiohopcolony/jobs/utils.py
aiohopcolony/topics/__init__.py
aiohopcolony/topics/exchange.py
aiohopcolony/topics/helper.py
aiohopcolony/topics/pika_helper.py
aiohopcolony/topics/queue.py
tests/__init__.py
tests/config.py
tests/test_auth.py
tests/test_docs.py
tests/test_drive.py
tests/test_init.py
tests/test_topics.py
aiohopcolony-0.1.9.dist-info/LICENSE
aiohopcolony-0.1.9.dist-info/METADATA
aiohopcolony-0.1.9.dist-info/WHEEL
aiohopcolony-0.1.9.dist-info/top_level.txt
aiohopcolony-0.1.9.dist-info/RECORD
